pydantic_mongo/__init__.py
pydantic_mongo/abstract_repository.py
pydantic_mongo/async_abstract_repository.py
pydantic_mongo/base_abstract_repository.py
pydantic_mongo/errors.py
pydantic_mongo/fields.py
pydantic_mongo/pagination.py
pydantic_mongo/py.typed
pydantic_mongo/version.py
pydantic_mongo-3.0.0.dist-info/licenses/LICENSE.md
pydantic_mongo-3.0.0.dist-info/METADATA
pydantic_mongo-3.0.0.dist-info/WHEEL
pydantic_mongo-3.0.0.dist-info/top_level.txt
pydantic_mongo-3.0.0.dist-info/RECORD
