Metadata-Version: 2.4
Name: pydantic-mongo
Version: 3.0.0
Summary: Document object mapper for pydantic and pymongo
Home-page: https://github.com/jefersondaniel/pydantic-mongo
Author: Jeferson Daniel
Author-email: jeferson.daniel412@gmail.com
License: MIT
Classifier: License :: OSI Approved :: MIT License
Classifier: Operating System :: OS Independent
Classifier: Programming Language :: Python :: 3.9
Classifier: Programming Language :: Python :: 3.10
Classifier: Programming Language :: Python :: 3.11
Requires-Python: >=3.8
License-File: LICENSE.md
Requires-Dist: pymongo<5.0,>=4.9
Requires-Dist: pydantic<3.0.0,>=2.0.2
Dynamic: author
Dynamic: author-email
Dynamic: classifier
Dynamic: description
Dynamic: description-content-type
Dynamic: home-page
Dynamic: license
Dynamic: license-file
Dynamic: requires-dist
Dynamic: requires-python
Dynamic: summary
